flexi_settings/__init__.py
flexi_settings/loaders.py
flexi_settings/settings.py
django_flexi_settings-0.1.1.dist-info/METADATA
django_flexi_settings-0.1.1.dist-info/WHEEL
django_flexi_settings-0.1.1.dist-info/entry_points.txt
django_flexi_settings-0.1.1.dist-info/top_level.txt
django_flexi_settings-0.1.1.dist-info/RECORD
