Metadata-Version: 2.1
Name: django-flexi-settings
Version: 0.1.1
Summary: Utilities for flexible configuration for Django.
Home-page: https://github.com/cedadev/django-flexi-settings
Author: Matt Pryor
Author-email: matt.pryor@stfc.ac.uk
License: UNKNOWN
Keywords: django flexible settings
Platform: UNKNOWN
Classifier: Programming Language :: Python
Requires-Dist: pyyaml
